lilizong_potato/__init__.py
lilizong_potato-0.1.0.dist-info/WHEEL
lilizong_potato-0.1.0.dist-info/entry_points.txt
lilizong_potato-0.1.0.dist-info/METADATA
lilizong_potato-0.1.0.dist-info/RECORD
