Metadata-Version: 2.3
Name: lilizong-potato
Version: 0.1.0
Summary: Add your description here
Requires-Dist: mcp[cli]>=1.19.0
Requires-Python: >=3.12
